rocketpy/Environment.py
rocketpy/Flight.py
rocketpy/Function.py
rocketpy/Rocket.py
rocketpy/SolidMotor.py
rocketpy/__init__.py
rocket.py-1.0.0.dist-info/LICENSE
rocket.py-1.0.0.dist-info/METADATA
rocket.py-1.0.0.dist-info/WHEEL
rocket.py-1.0.0.dist-info/top_level.txt
rocket.py-1.0.0.dist-info/RECORD
