Metadata-Version: 2.1
Name: rocket.py
Version: 1.0.0
Summary: Advanced 6-DOF trajectory simulation for High-Power Rocketry.
Home-page: https://github.com/giovaniceotto/RocketPy
Author: Giovani Hidalgo Ceotto
Author-email: ghceotto@gmail.com
Maintainer: RocketPy Developers
License: UNKNOWN
Platform: UNKNOWN
Classifier: Programming Language :: Python :: 3
Classifier: License :: OSI Approved :: MIT License
Classifier: Operating System :: OS Independent
Requires-Python: >=3.6
Requires-Dist: numpy (>=1.0)
Requires-Dist: scipy (>=1.0)
Requires-Dist: matplotlib (>=3.0)
Requires-Dist: requests
